Workbook

Sheet Info
A1: INGRAM MICRO — IBM S&S Renewals · Hoja de Información
A2: Quote: 0027446898 · Generado: 20/04/2026 17:41
A3: CANAL
C4: CANAL | D4: WISEVISION DE COLOMBIA S A S | F4: ICN | G4: 521400 | I4: SBID/QUOTE | J4: 0027446898
C5: CLIENTE | D5: AXA COLPATRIA SEGUROS S.A. | F5: SITE | G5: 0003767373-AXA COLPATRIA SEGUROS S.A., CR 7 24 89 PSO 7, COL
C6: CÓDIGO CANAL | D6: 0004048795 | F6: Select Territory | G6: Yes
A8: CLASIFICACIÓN
C9: Cliente | D9: AXA COLPATRIA SEGUROS S.A. | F9: Incentivos | I9: Margen Cadena | J9: =J10+J11
C10: Banda | D10: BL | F10: BP | G10: INGRAM | I10: Margen Canal | J10: 0.03
C11: Gobierno | D11: No | F11: CVR Renew | I11: Margen Ingram | J11: 0.021
C12: Categoría | D12: S&S | F12: 0.02 | G12: 0.02
C13: Cliente | D13: Co-Led | F13: CVR OnTime
F14: 0.02 | G14: 0.01

Sheet Calculadora
A1: CALCULADORA — IBM S&S Renewals · Ingram Micro
B3: INGRAM / BP | F3: Fechas | H3: Producto | L3: Precios IBM | P3: Cadena de precios | Z3: Incentivos Total — BP | AJ3: Después de incentivos
B4: On Time | C4: Renew | D4: On Time | E4: Renew
B5: On Time | C5: Renew | D5: On Time | E5: Renew | F5: Fecha de Inicio | G5: Fecha de Fin | H5: NP | I5: Descripción | J5: Precio Unitario Banda sin Uplift | K5: Precio Unitario Banda con Uplift | L5: Cantidad | M5: Precio Banda | N5: Descuento | O5: Precio Cliente Final | P5: Margen canal | Q5: V/unit Venta | R5: Costo Canal | S5: Costo Ingram Unit | T5: Precio Compra Ingram | U5: Costo Ingram | V5: Margen Ingram TX | W5: Año | X5: Precio unitario cliente final | Z5: % Incentivos Total | AA5: Incentivo | AB5: % BP | AC5: Total Incentivos | AD5: On time | AE5: Renew | AF5: Incentivo total Unitario | AG5: Incentivo BP Unitario | AH5: Incentivo Ingram Unitario | AJ5: Costo Total BP | AK5: Costo Ingram Total | AL5: Margen antes de incentivos | AM5: Margen después de incentivos
B6: =Info!$G$14 | C6: =Info!$G$12 | D6: =Info!$F$14 | E6: =Info!$F$12 | F6: 46174 | G6: 46538 | H6: E11H8ZX | I6: IBM Guardium Aggregator Software Appliance Install Annual SW S&S Rnwl | J6: 333.86 | K6: 333.86 | L6: 1 | M6: =K6*L6 | N6: 0 | O6: =M6*(1-N6) | P6: =Info!$J$10 | Q6: =R6/L6 | R6: =O6*(1-P6) | S6: =U6/L6 | T6: =O6*(1-Info!$J$9) | U6: =O6*(1-Info!$J$11) | V6: =IF(R6<>0,1-U6/R6,"") | W6: Año 1 | X6: =O6/L6 | Z6: =Info!$F$12+Info!$G$12+Info!$F$14+Info!$G$14 | AA6: =Z6*O6 | AB6: =D6+E6 | AC6: =AB6*O6 | AD6: =O6*D6 | AE6: =O6*E6 | AF6: =IF(L6<>0,AA6/L6,"") | AG6: =IF(L6<>0,AC6/L6,"") | AH6: =IF(L6<>0,(AA6-AC6)/L6,"") | AJ6: =R6-AC6 | AK6: =U6-AA6 | AL6: =IF(R9<>0,1-(AK9/R9),"") | AM6: =IF(AJ9<>0,1-(AK9/AJ9),"")
B7: =Info!$G$14 | C7: =Info!$G$12 | D7: =Info!$F$14 | E7: =Info!$F$12 | F7: 46174 | G7: 46538 | H7: E11H2ZX | I7: IBM Guardium Collector Software Appliance Install Annual SW S&S Rnwl | J7: 332.76 | K7: 332.76 | L7: 3 | M7: =K7*L7 | N7: 0 | O7: =M7*(1-N7) | P7: =Info!$J$10 | Q7: =R7/L7 | R7: =O7*(1-P7) | S7: =U7/L7 | T7: =O7*(1-Info!$J$9) | U7: =O7*(1-Info!$J$11) | V7: =IF(R7<>0,1-U7/R7,"") | W7: Año 1 | X7: =O7/L7 | Z7: =Info!$F$12+Info!$G$12+Info!$F$14+Info!$G$14 | AA7: =Z7*O7 | AB7: =D7+E7 | AC7: =AB7*O7 | AD7: =O7*D7 | AE7: =O7*E7 | AF7: =IF(L7<>0,AA7/L7,"") | AG7: =IF(L7<>0,AC7/L7,"") | AH7: =IF(L7<>0,(AA7-AC7)/L7,"") | AJ7: =R7-AC7 | AK7: =U7-AA7 | AL7: =IF(R9<>0,1-(AK9/R9),"") | AM7: =IF(AJ9<>0,1-(AK9/AJ9),"")
B8: =Info!$G$14 | C8: =Info!$G$12 | D8: =Info!$F$14 | E8: =Info!$F$12 | F8: 46174 | G8: 46538 | H8: E0MQPLL | I8: GUARD DATA PRTCTN BIG DATA RVU ML ANNUAL SW S&S RNWL | J8: 1809.16 | K8: 1809.16 | L8: 12 | M8: =K8*L8 | N8: 0 | O8: =M8*(1-N8) | P8: =Info!$J$10 | Q8: =R8/L8 | R8: =O8*(1-P8) | S8: =U8/L8 | T8: =O8*(1-Info!$J$9) | U8: =O8*(1-Info!$J$11) | V8: =IF(R8<>0,1-U8/R8,"") | W8: Año 1 | X8: =O8/L8 | Z8: =Info!$F$12+Info!$G$12+Info!$F$14+Info!$G$14 | AA8: =Z8*O8 | AB8: =D8+E8 | AC8: =AB8*O8 | AD8: =O8*D8 | AE8: =O8*E8 | AF8: =IF(L8<>0,AA8/L8,"") | AG8: =IF(L8<>0,AC8/L8,"") | AH8: =IF(L8<>0,(AA8-AC8)/L8,"") | AJ8: =R8-AC8 | AK8: =U8-AA8 | AL8: =IF(R9<>0,1-(AK9/R9),"") | AM8: =IF(AJ9<>0,1-(AK9/AJ9),"")
L9: Total | O9: =SUM(O6:O8) | R9: =SUM(R6:R8) | T9: =SUM(T6:T8) | U9: =SUM(U6:U8) | V9: =IF(R9<>0,1-U9/R9,"") | AA9: =SUM(AA6:AA8) | AC9: =SUM(AC6:AC8) | AD9: =SUM(AD6:AD8) | AE9: =SUM(AE6:AE8) | AJ9: =SUM(AJ6:AJ8) | AK9: =SUM(AK6:AK8)
L10: Nota de descuento | O10: =AC9

Sheet Cotización
A1: INGRAM MICRO Colombia · IBM Authorized Reseller
A2: IBM Software Subscription & Support (S&S) — Cotización al Canal
B3: Canal: | C3: =Info!D4
B4: Cliente Final: | C4: =Info!D5
B5: Fabricante: | C5: IBM - International Business Machine
B6: Fecha: | C6: =TODAY()
B8: ="A continuación, se comparten precios aprobados bajo SBID "&Info!J4&" para el cliente "&C4
B10: RESUMEN PROPUESTA ECONÓMICA
B11: Fecha de Inicio | C11: Fecha de Fin | D11: Parte Número | E11: Descripción | F11: Cantidad | G11: Precio Cliente Final (MEP) | H11: Margen Canal | I11: V/unit Canal | J11: Costo Total Canal
B12: =Calculadora!F6 | C12: =Calculadora!G6 | D12: =Calculadora!H6 | E12: =Calculadora!I6 | F12: =Calculadora!L6 | G12: =Calculadora!O6 | H12: =Calculadora!P6 | I12: =Calculadora!Q6 | J12: =Calculadora!R6
B13: =Calculadora!F7 | C13: =Calculadora!G7 | D13: =Calculadora!H7 | E13: =Calculadora!I7 | F13: =Calculadora!L7 | G13: =Calculadora!O7 | H13: =Calculadora!P7 | I13: =Calculadora!Q7 | J13: =Calculadora!R7
B14: =Calculadora!F8 | C14: =Calculadora!G8 | D14: =Calculadora!H8 | E14: =Calculadora!I8 | F14: =Calculadora!L8 | G14: =Calculadora!O8 | H14: =Calculadora!P8 | I14: =Calculadora!Q8 | J14: =Calculadora!R8
B15: TOTAL: | G15: =SUM(G12:G14) | J15: =SUM(J12:J14)
B16: Nota de descuento | J16: =Calculadora!O10
B18: Los precios aquí expresados son los precios a los que INGRAM MICRO SAS facturará al Canal. El precio al Cliente debe ser definido por el Canal o por el fabricante en su propuesta según las condiciones del negocio.
B21: Margen transaccional aproximado incluyendo nota de descuento: 7.0% Detalle de incentivos:
C22: Parte Número | D22: Descripción | E22: Cantidad | F22: Total Incentivo | G22: On time | H22: Renew
C23: =Calculadora!H6 | D23: =Calculadora!I6 | E23: =Calculadora!L6 | F23: =Calculadora!AC6 | G23: =Calculadora!AD6 | H23: =Calculadora!AE6
C24: =Calculadora!H7 | D24: =Calculadora!I7 | E24: =Calculadora!L7 | F24: =Calculadora!AC7 | G24: =Calculadora!AD7 | H24: =Calculadora!AE7
C25: =Calculadora!H8 | D25: =Calculadora!I8 | E25: =Calculadora!L8 | F25: =Calculadora!AC8 | G25: =Calculadora!AD8 | H25: =Calculadora!AE8
C26: Total | F26: =SUM(F23:F25) | G26: =SUM(G23:G25) | H26: =SUM(H23:H25)
B28: Condiciones Generales de Cotización – INGRAM MICRO S.A.S.
B29: • Incentivos sujetos a cambio de programa Partner Plus de IBM
B30: • Los precios enviados en esta propuesta están aprobados por IBM bajo el SBID
B31: • El manejo de los SBID está regulado por lo establecido en el BPA firmado con IBM.
B32: • Para procesar este SBID, Ingram Micro podrá solicitar la Orden de Compra (OC) enviada por el cliente final.
B33: • Las notas de descuento se generan de manera independiente tal y como las realiza el fabricante.
B34: • Propuesta válida por 30 días. Los precios están expresados en USD y sujetos a cambios según las políticas de IBM.
B35: • Se respetará el Precio Máximo para el Usuario Final (MEP), según lo indicado por IBM y el distribuidor autorizado.
B36: • Los valores aquí mencionados no incluyen IVA, dicho impuesto será cargado en la factura.
B38: Angela Herrera · Business Development Manager IBM · angela.herrera@ingrammicro.com · +57 316 696 91 38

Sheet Compra
A1: ORDEN DE COMPRA INTERNA — IBM S&S Renewals · Ingram Micro
A2: TIPO DE SOLICITUD | B2: Código Canal | C2: Material | D2: IVA | E2: Número de parte | F2: Descripción | G2: Cantidad | H2: Precio de COMPRA UNITARIO | I2: Valor Acop 1 unitario | J2: Valor Acop 2 unitario | K2: Valor Pocc | L2: Nro. de Acop/Pocc, Quote, Deal, Soup, OPG | M2: Nota descuento Si / No | N2: SKU | O2: Comentarios | P2: Margen | Q2: Ship To | R2: Precio de Venta UNITARIO | S2: TERMINO DE PAGO | T2: FIORI | W2: Nombre del Cliente: | X2: =Info!D5
A3: Compra | B3: =Info!$D$6 | F3: =Calculadora!H6 | G3: =Calculadora!L6 | H3: =Calculadora!S6 | I3: N/A | J3: N/A | K3: =H3*G3 | L3: =Info!$J$4 | M3: Si | N3: N/A | O3: El margen real de la NV es el 2,06%, Se factura fecha de emisión de la factura | P3: =IF(S3<>0,1-(H3/S3),"") | Q3: Empresa, contacto celular, dirección, ciudad, etc. | R3: =Calculadora!Q6 | S3: =Calculadora!Q6 | T3: Estándar del canal
A4: Compra | B4: =Info!$D$6 | F4: =Calculadora!H7 | G4: =Calculadora!L7 | H4: =Calculadora!S7 | I4: N/A | J4: N/A | K4: =H4*G4 | L4: =Info!$J$4 | M4: Si | N4: N/A | O4: El margen real de la NV es el 2,06%, Se factura fecha de emisión de la factura | P4: =IF(S4<>0,1-(H4/S4),"") | Q4: Empresa, contacto celular, dirección, ciudad, etc. | R4: =Calculadora!Q7 | S4: =Calculadora!Q7 | T4: Estándar del canal | W4: End User Segmentation: | X4: =Info!D4
A5: Compra | B5: =Info!$D$6 | F5: =Calculadora!H8 | G5: =Calculadora!L8 | H5: =Calculadora!S8 | I5: N/A | J5: N/A | K5: =H5*G5 | L5: =Info!$J$4 | M5: Si | N5: N/A | O5: El margen real de la NV es el 2,06%, Se factura fecha de emisión de la factura | P5: =IF(S5<>0,1-(H5/S5),"") | Q5: Empresa, contacto celular, dirección, ciudad, etc. | R5: =Calculadora!Q8 | S5: =Calculadora!Q8 | T5: Estándar del canal | X5: CO-LED – Select Territory
W6: Nombre del Reseller: | X6: =Info!D4
W7: Site Number: | X7: =Info!G5
B8: Resumen para importar a Xvantage | W8: Tipo de Licencia: | X8: Renew
B9: Material | C9: Cant. | D9: Venta Unit U$ | E9: Costo Unit U$ | F9: Importar Xvantage | G9: Quote X4A | W9: Número de SBID: | X9: =Info!J4
B10: =F3 | C10: =G3 | D10: =R3 | E10: =H3 | F10: =C10&","&D10&","&TEXT(ROUNDUP(E10,2),"0.00")&",,,,"&TEXT(ROUNDUP(E10,2),"0.00") | W10: Quote Number:
B11: =F4 | C11: =G4 | D11: =R4 | E11: =H4 | F11: =C11&","&D11&","&TEXT(ROUNDUP(E11,2),"0.00")&",,,,"&TEXT(ROUNDUP(E11,2),"0.00")
B12: =F5 | C12: =G5 | D12: =R5 | E12: =H5 | F12: =C12&","&D12&","&TEXT(ROUNDUP(E12,2),"0.00")&",,,,"&TEXT(ROUNDUP(E12,2),"0.00")
